discord_check/__init__.py
discord_check-1.0.3.dist-info/LICENSE
discord_check-1.0.3.dist-info/METADATA
discord_check-1.0.3.dist-info/WHEEL
discord_check-1.0.3.dist-info/top_level.txt
discord_check-1.0.3.dist-info/RECORD
