Metadata-Version: 2.1
Name: discord_check
Version: 1.0.3
Summary: A module check token discord active
Project-URL: GitHub, https://github.com/desotana/discord_check/
License-File: LICENSE
